duwi_smarthome_sdk_dev
test
